{
    "title1": "Empower business",
    "title2": "Our Mission is to:",
    "subtitle": "Professionals focused on helping your brand <br/>  grow and move forward.",
    "values": [
        {
            "title": "To achieve any goal",
            "text": ""
        },
        {
            "title": "For any workflow",
            "text": ""
        },
        {
            "title": "In any setting",
            "text": ""
        },
        {
            "title": "Through a range of products and services",
            "text": ""
        },
        {
            "title": "In smart, efficient and effective ways",
            "text": ""
        }
    ]
}